src/__init__.py
src/optimizers.py
src/preprocessing.py
src/sprout.py
src/utils.py
pySPROUT-2.0.0.dist-info/METADATA
pySPROUT-2.0.0.dist-info/WHEEL
pySPROUT-2.0.0.dist-info/top_level.txt
pySPROUT-2.0.0.dist-info/RECORD
