Metadata-Version: 2.1
Name: pySPROUT
Version: 2.0.0
Summary: SPROUT: spectral sparsification helps restore the spatial structure at single-cell resolution.
Home-page: https://github.com/deepomicslab/SPROUT/
Author: Jingwan WANG
Author-email: wanwang6-c@my.cityu.edu.hk
License: MIT
Platform: UNKNOWN
Requires-Dist: umap-learn
Requires-Dist: loess
Requires-Dist: tasklogger
Requires-Dist: random2
Requires-Dist: scipy
